{
	"name": "ai",
	"events": [
		{
			"eventType": "block",
			"conditions": [
				{
					"id": "every-tick",
					"objectClass": "System",
					"sid": 564780676241988
				}
			],
			"actions": [],
			"sid": 340240533574156,
			"children": [
				{
					"eventType": "block",
					"conditions": [
						{
							"id": "compare-two-values",
							"objectClass": "System",
							"sid": 886211500208522,
							"parameters": {
								"first-value": "input_0_type",
								"comparison": 0,
								"second-value": "\"Bot\""
							}
						}
					],
					"actions": [
						{
							"callFunction": "evaluateInputAi",
							"sid": 681214966370214,
							"parameters": [
								"0"
							]
						}
					],
					"sid": 547624604423619
				},
				{
					"eventType": "block",
					"conditions": [
						{
							"id": "compare-two-values",
							"objectClass": "System",
							"sid": 982053784475521,
							"parameters": {
								"first-value": "input_1_type",
								"comparison": 0,
								"second-value": "\"Bot\""
							}
						}
					],
					"actions": [
						{
							"callFunction": "evaluateInputAi",
							"sid": 798685644087390,
							"parameters": [
								"1"
							]
						}
					],
					"sid": 894208262420743
				}
			]
		},
		{
			"functionName": "evaluateInputAi",
			"functionDescription": "Evaluates ai input.",
			"functionCategory": "input",
			"functionReturnType": "none",
			"functionIsAsync": false,
			"functionParameters": [
				{
					"name": "player",
					"type": "number",
					"initialValue": "0",
					"comment": "",
					"sid": 607120315232752
				}
			],
			"eventType": "function-block",
			"conditions": [],
			"actions": [],
			"sid": 350221551669785,
			"children": [
				{
					"eventType": "script",
					"script": "let pad = Pad.find(runtime, localVars.player);\nlet ball = runtime.objects.ball.getFirstInstance();\n\n\nif (ball !== null && ball.y < ball.layout.height / 2 && Utils.getVectorY(ball.behaviors.Bullet.speed, ball.behaviors.Bullet.angleOfMotion) < 0) {\n\truntime.callFunction('aiFollowBall', pad.instVars.player, ball.uid);\n}\n\nif (ball !== null && ball.y > ball.layout.height / 2) {\n\truntime.callFunction('aiCenterPosition', pad.instVars.player, ball.uid);\n}\n\nif (ball !== null && Utils.getVectorY(ball.behaviors.Bullet.speed, ball.behaviors.Bullet.angleOfMotion) > 0) {\n\truntime.callFunction('aiCenterPosition', pad.instVars.player, ball.uid);\n}\n\nif (ball === null) {\n\truntime.callFunction('aiCenterPosition', pad.instVars.player, 0);\n}"
				},
				{
					"eventType": "block",
					"conditions": [],
					"actions": [],
					"sid": 993125224695993,
					"children": [
						{
							"eventType": "block",
							"conditions": [
								{
									"id": "compare-two-values",
									"objectClass": "System",
									"sid": 875512597511239,
									"parameters": {
										"first-value": "ball.Count",
										"comparison": 4,
										"second-value": "0"
									}
								},
								{
									"id": "compare-two-values",
									"objectClass": "System",
									"sid": 635032705665482,
									"parameters": {
										"first-value": "ball.Y",
										"comparison": 2,
										"second-value": "LayoutHeight / 2"
									}
								}
							],
							"actions": [
								{
									"callFunction": "aiFollowBall",
									"sid": 629431414756063,
									"parameters": [
										"pad.player",
										"ball.UID"
									]
								}
							],
							"sid": 466003114354139,
							"disabled": true
						},
						{
							"eventType": "block",
							"conditions": [
								{
									"id": "compare-two-values",
									"objectClass": "System",
									"sid": 585316551369215,
									"parameters": {
										"first-value": "ball.Count",
										"comparison": 4,
										"second-value": "0"
									}
								},
								{
									"id": "compare-two-values",
									"objectClass": "System",
									"sid": 319812816081613,
									"parameters": {
										"first-value": "ball.Y",
										"comparison": 4,
										"second-value": "LayoutHeight / 2"
									}
								}
							],
							"actions": [
								{
									"callFunction": "aiCenterPosition",
									"sid": 153050181913122,
									"parameters": [
										"pad.player",
										"ball.UID"
									]
								}
							],
							"sid": 101135332689398,
							"disabled": true
						},
						{
							"eventType": "block",
							"conditions": [
								{
									"id": "compare-two-values",
									"objectClass": "System",
									"sid": 145343406297121,
									"parameters": {
										"first-value": "ball.Count",
										"comparison": 4,
										"second-value": "0"
									}
								}
							],
							"actions": [
								{
									"callFunction": "aiCenterPosition",
									"sid": 953875763574462,
									"parameters": [
										"pad.player",
										"ball.UID"
									]
								}
							],
							"sid": 242445575815061,
							"disabled": true
						},
						{
							"eventType": "block",
							"conditions": [
								{
									"id": "compare-two-values",
									"objectClass": "System",
									"sid": 488763535663526,
									"parameters": {
										"first-value": "ball.Count",
										"comparison": 0,
										"second-value": "0"
									}
								}
							],
							"actions": [
								{
									"callFunction": "aiCenterPosition",
									"sid": 887372418529299,
									"parameters": [
										"pad.player",
										"ball.UID"
									]
								}
							],
							"sid": 673248206154376,
							"disabled": true
						}
					]
				}
			]
		},
		{
			"functionName": "aiFollowBall",
			"functionDescription": "Makes an ia follow the ball.",
			"functionCategory": "ai",
			"functionReturnType": "none",
			"functionIsAsync": false,
			"functionParameters": [
				{
					"name": "padIndex",
					"type": "number",
					"initialValue": "0",
					"comment": "",
					"sid": 778928287780151
				},
				{
					"name": "ballUid",
					"type": "number",
					"initialValue": "0",
					"comment": "",
					"sid": 157716554725864
				}
			],
			"eventType": "function-block",
			"conditions": [],
			"actions": [],
			"sid": 724711701038804,
			"children": [
				{
					"eventType": "block",
					"conditions": [
						{
							"id": "pick-by-evaluate",
							"objectClass": "System",
							"sid": 209849464048521,
							"parameters": {
								"object": "pad",
								"expression": "pad.player"
							}
						},
						{
							"id": "pick-by-unique-id",
							"objectClass": "ball",
							"sid": 755474347703753,
							"parameters": {
								"unique-id": "ballUid"
							}
						}
					],
					"actions": [],
					"sid": 936500919683310,
					"children": [
						{
							"eventType": "block",
							"conditions": [
								{
									"id": "compare-two-values",
									"objectClass": "System",
									"sid": 779403649149607,
									"parameters": {
										"first-value": "ball.X",
										"comparison": 2,
										"second-value": "pad.X  - pad.Width / 2"
									}
								}
							],
							"actions": [
								{
									"type": "script",
									"script": "let pad = Pad.find(runtime, localVars.padIndex);\npad.simulateLeft();"
								}
							],
							"sid": 382976047080082
						},
						{
							"eventType": "block",
							"conditions": [
								{
									"id": "compare-two-values",
									"objectClass": "System",
									"sid": 572351926059272,
									"parameters": {
										"first-value": "ball.X",
										"comparison": 4,
										"second-value": "pad.X  + pad.Width / 2"
									}
								}
							],
							"actions": [
								{
									"type": "script",
									"script": "let pad = Pad.find(runtime, localVars.padIndex);\npad.simulateRight();"
								}
							],
							"sid": 600913421445000
						}
					]
				}
			]
		},
		{
			"functionName": "aiCenterPosition",
			"functionDescription": "Makes an ai set their position to the center.",
			"functionCategory": "ai",
			"functionReturnType": "none",
			"functionIsAsync": false,
			"functionParameters": [
				{
					"name": "padIndex",
					"type": "number",
					"initialValue": "0",
					"comment": "",
					"sid": 963647962007172
				},
				{
					"name": "ballUid",
					"type": "number",
					"initialValue": "0",
					"comment": "",
					"sid": 317106915790908
				}
			],
			"eventType": "function-block",
			"conditions": [],
			"actions": [],
			"sid": 836922949640537,
			"children": [
				{
					"eventType": "block",
					"conditions": [
						{
							"id": "pick-by-evaluate",
							"objectClass": "System",
							"sid": 672148508560387,
							"parameters": {
								"object": "pad",
								"expression": "pad.player"
							}
						},
						{
							"id": "pick-by-unique-id",
							"objectClass": "ball",
							"sid": 279452238726742,
							"parameters": {
								"unique-id": "ballUid"
							}
						}
					],
					"actions": [],
					"sid": 284638872271832,
					"children": [
						{
							"eventType": "block",
							"conditions": [
								{
									"id": "compare-two-values",
									"objectClass": "System",
									"sid": 747559458745973,
									"parameters": {
										"first-value": "LayoutWidth / 2 - pad.Width / 2",
										"comparison": 3,
										"second-value": "pad.X"
									}
								}
							],
							"actions": [
								{
									"type": "script",
									"script": "let pad = Pad.find(runtime, localVars.padIndex);\npad.simulateLeft();"
								}
							],
							"sid": 311453813830400
						},
						{
							"eventType": "block",
							"conditions": [
								{
									"id": "compare-two-values",
									"objectClass": "System",
									"sid": 347634549244055,
									"parameters": {
										"first-value": "LayoutWidth / 2 + pad.Width / 2",
										"comparison": 5,
										"second-value": "pad.X"
									}
								}
							],
							"actions": [
								{
									"type": "script",
									"script": "let pad = Pad.find(runtime, localVars.padIndex);\npad.simulateRight();"
								}
							],
							"sid": 671551227781009
						}
					]
				}
			]
		}
	],
	"sid": 538112269311819
}